sonucv/__init__.py
sonucv/resume.py
sonucv-1.2.dist-info/METADATA
sonucv-1.2.dist-info/WHEEL
sonucv-1.2.dist-info/entry_points.txt
sonucv-1.2.dist-info/top_level.txt
sonucv-1.2.dist-info/RECORD
